animal_sounds/__init__.py
animal_sounds/admin.py
animal_sounds/model.py
animal_sounds/models.py
patch_tracker/__init__.py
patch_tracker/admin.py
patch_tracker/model.py
patch_tracker/models.py
dans_netbox_plugins-0.4.dist-info/LICENSE
dans_netbox_plugins-0.4.dist-info/METADATA
dans_netbox_plugins-0.4.dist-info/WHEEL
dans_netbox_plugins-0.4.dist-info/top_level.txt
dans_netbox_plugins-0.4.dist-info/RECORD
