Metadata-Version: 2.1
Name: dans-netbox-plugins
Version: 0.4
Summary: creating example and Pilot"s first plugin
Home-page: https://github.com/dmurphy112/public
Author: daniel murphy
Author-email: dev@danielmurphy.email
License: Apache 2.0
Platform: UNKNOWN
Classifier: Programming Language :: Python :: 3
Classifier: License :: OSI Approved :: MIT License
Classifier: Operating System :: OS Independent
Requires-Python: >=3.6
